life_span_storage
