Metadata-Version: 2.1
Name: life-span-storage
Version: 0.0.6
Summary: Dash Store Component
Author: s_matsumoto <s_matsumoto@thinkup-sol.co.jp>
License: MIT
Classifier: Framework :: Dash
License-File: LICENSE
